nelder_mead/__init__.py
nelder_mead/alg.py
nelder_mead-1.0.1.dist-info/METADATA
nelder_mead-1.0.1.dist-info/RECORD
nelder_mead-1.0.1.dist-info/WHEEL
nelder_mead-1.0.1.dist-info/top_level.txt
