Metadata-Version: 2.1
Name: nelder-mead
Version: 1.0.1
Summary: Nelder-Mead for numerical optimization in Python
Home-page: https://github.com/nmasahiro/nelder_mead
Author: Masahiro Nomura
Author-email: masahironomura5325@gmail.com
Maintainer: Masahiro Nomura
Maintainer-email: masahironomura5325@gmail.com
License: MIT
Keywords: optimization,Nelder-Mead
Platform: UNKNOWN
Classifier: Intended Audience :: Science/Research
Classifier: Intended Audience :: Education
Classifier: Intended Audience :: Other Audience
Classifier: Topic :: Scientific/Engineering
Classifier: Topic :: Scientific/Engineering :: Mathematics
Classifier: Topic :: Scientific/Engineering :: Artificial Intelligence
Classifier: Operating System :: OS Independent
Classifier: Programming Language :: Python :: 3
Classifier: Development Status :: 4 - Beta
Classifier: Environment :: Console
Classifier: License :: OSI Approved :: MIT License
Requires: numpy
Requires: functools
